mdrec/__init__.py
mdrec/component.py
mdrec/mdrec.py
mdrec-0.1.1.dist-info/DESCRIPTION.rst
mdrec-0.1.1.dist-info/METADATA
mdrec-0.1.1.dist-info/RECORD
mdrec-0.1.1.dist-info/WHEEL
mdrec-0.1.1.dist-info/entry_points.txt
mdrec-0.1.1.dist-info/metadata.json
mdrec-0.1.1.dist-info/top_level.txt
