Metadata-Version: 2.0
Name: mdrec
Version: 0.1.1
Summary: record python object to markdown file & convert to html.
Home-page: https://github.com/knknkn1162/mdrec
Author: knknkn1162
Author-email: knknkn1162@gmail.com
License: MIT
Platform: UNKNOWN
Classifier: Programming Language :: Python :: 3 :: Only
Classifier: Framework :: IPython
Requires-Dist: pandas
Requires-Dist: grip
Requires-Dist: pytablewriter
Requires-Dist: ipython
Requires-Dist: pyyaml
